Workbook

Sheet Enterprise_Data
C3: 2020 | D3: =C3+1 -> 2021 | E3: =D3+1 -> 2022 | F3: =E3+1 -> 2023 | G3: =F3+1 -> 2024 | H3: =G3+1 -> 2025 | K3: 2020 | L3: =K3+1 -> 2021 | M3: =L3+1 -> 2022 | N3: =M3+1 -> 2023 | O3: =N3+1 -> 2024 | P3: =O3+1 -> 2025
B5: NoR | C5: 100 | D5: =C5*(1+Hypothesis!$C$3) -> 120 | E5: =D5*(1+Hypothesis!$C$3) -> 144 | F5: =E5*(1+Hypothesis!$C$3) -> 172.8 | G5: =F5*(1+Hypothesis!$C$3) -> 207.36 | H5: =G5*(1+Hypothesis!$C$3) -> 248.832 | J5: op tangible asset | K5: 30 | L5: =K5*(1+Hypothesis!$F$3) -> 32.4 | M5: =L5*(1+Hypothesis!$F$3) -> 34.992 | N5: =M5*(1+Hypothesis!$F$3) -> 37.79136 | O5: =N5*(1+Hypothesis!$F$3) -> 40.814669 | P5: =O5*(1+Hypothesis!$F$3) -> 44.079842
B6: Cost of good sold | C6: =SUM(C7:C9) -> -50 | D6: =SUM(D7:D9) -> -57.5 | E6: =SUM(E7:E9) -> -66.125 | F6: =SUM(F7:F9) -> -76.04375 | G6: =SUM(G7:G9) -> -87.450312 | H6: =SUM(H7:H9) -> -100.56786 | J6: op intangible asset | K6: 12 | L6: =K6*(1+Hypothesis!$F$3) -> 12.96 | M6: =L6*(1+Hypothesis!$F$3) -> 13.9968 | N6: =M6*(1+Hypothesis!$F$3) -> 15.116544 | O6: =N6*(1+Hypothesis!$F$3) -> 16.325868 | P6: =O6*(1+Hypothesis!$F$3) -> 17.631937
B7: direct material cost | C7: -30 | D7: =(C7*(1+Hypothesis!$C$4)) -> -34.5 | E7: =(D7*(1+Hypothesis!$C$4)) -> -39.675 | F7: =(E7*(1+Hypothesis!$C$4)) -> -45.62625 | G7: =(F7*(1+Hypothesis!$C$4)) -> -52.470187 | H7: =(G7*(1+Hypothesis!$C$4)) -> -60.340716 | J7: permanent inventories | K7: 8 | L7: =K7*(1+Hypothesis!$F$3) -> 8.64 | M7: =L7*(1+Hypothesis!$F$3) -> 9.3312 | N7: =M7*(1+Hypothesis!$F$3) -> 10.077696 | O7: =N7*(1+Hypothesis!$F$3) -> 10.883912 | P7: =O7*(1+Hypothesis!$F$3) -> 11.754625
B8: direct production service cost | C8: -10 | D8: =(C8*(1+Hypothesis!$C$4)) -> -11.5 | E8: =(D8*(1+Hypothesis!$C$4)) -> -13.225 | F8: =(E8*(1+Hypothesis!$C$4)) -> -15.20875 | G8: =(F8*(1+Hypothesis!$C$4)) -> -17.490062 | H8: =(G8*(1+Hypothesis!$C$4)) -> -20.113572 | J8: CAPEX | K8: =SUM(K5:K7) -> 50 | L8: =SUM(L5:L7) -> 54 | M8: =SUM(M5:M7) -> 58.32 | N8: =SUM(N5:N7) -> 62.9856 | O8: =SUM(O5:O7) -> 68.024448 | P8: =SUM(P5:P7) -> 73.466404
B9: direct labour cost | C9: -10 | D9: =(C9*(1+Hypothesis!$C$4)) -> -11.5 | E9: =(D9*(1+Hypothesis!$C$4)) -> -13.225 | F9: =(E9*(1+Hypothesis!$C$4)) -> -15.20875 | G9: =(F9*(1+Hypothesis!$C$4)) -> -17.490062 | H9: =(G9*(1+Hypothesis!$C$4)) -> -20.113572 | J9: trade receivables | K9: 25 | L9: =K9*(1+Hypothesis!$F$3) -> 27 | M9: =L9*(1+Hypothesis!$F$3) -> 29.16 | N9: =M9*(1+Hypothesis!$F$3) -> 31.4928 | O9: =N9*(1+Hypothesis!$F$3) -> 34.012224 | P9: =O9*(1+Hypothesis!$F$3) -> 36.733202
B10: GP | C10: =C5+C6 -> 50 | D10: =D5+D6 -> 62.5 | E10: =E5+E6 -> 77.875 | F10: =F5+F6 -> 96.75625 | G10: =G5+G6 -> 119.90969 | H10: =H5+H6 -> 148.26414 | J10: trade payables | K10: -16 | L10: =K10*(1+Hypothesis!$F$3) -> -17.28 | M10: =L10*(1+Hypothesis!$F$3) -> -18.6624 | N10: =M10*(1+Hypothesis!$F$3) -> -20.155392 | O10: =N10*(1+Hypothesis!$F$3) -> -21.767823 | P10: =O10*(1+Hypothesis!$F$3) -> -23.509249
B11: Operating cost | C11: =SUM(C12:C18) -> -19 | D11: =SUM(D12:D18) -> -21.85 | E11: =SUM(E12:E18) -> -25.1275 | F11: =SUM(F12:F18) -> -28.896625 | G11: =SUM(G12:G18) -> -33.231119 | H11: =SUM(H12:H18) -> -38.215787 | J11: TWC | K11: =SUM(K9:K10) -> 9 | L11: =SUM(L9:L10) -> 9.72 | M11: =SUM(M9:M10) -> 10.4976 | N11: =SUM(N9:N10) -> 11.337408 | O11: =SUM(O9:O10) -> 12.244401 | P11: =SUM(P9:P10) -> 13.223953
B12: Personal cost | C12: -5 | D12: =(C12*(1+Hypothesis!$C$4)) -> -5.75 | E12: =(D12*(1+Hypothesis!$C$4)) -> -6.6125 | F12: =(E12*(1+Hypothesis!$C$4)) -> -7.604375 | G12: =(F12*(1+Hypothesis!$C$4)) -> -8.7450312 | H12: =(G12*(1+Hypothesis!$C$4)) -> -10.056786 | J12: inventories | K12: 5 | L12: =K12*(1+Hypothesis!$F$3) -> 5.4 | M12: =L12*(1+Hypothesis!$F$3) -> 5.832 | N12: =M12*(1+Hypothesis!$F$3) -> 6.29856 | O12: =N12*(1+Hypothesis!$F$3) -> 6.8024448 | P12: =O12*(1+Hypothesis!$F$3) -> 7.3466404
B13: research cost | C13: -2 | D13: =(C13*(1+Hypothesis!$C$4)) -> -2.3 | E13: =(D13*(1+Hypothesis!$C$4)) -> -2.645 | F13: =(E13*(1+Hypothesis!$C$4)) -> -3.04175 | G13: =(F13*(1+Hypothesis!$C$4)) -> -3.4980125 | H13: =(G13*(1+Hypothesis!$C$4)) -> -4.0227144 | J13: other op receivables | K13: 4 | L13: =K13*(1+Hypothesis!$F$3) -> 4.32 | M13: =L13*(1+Hypothesis!$F$3) -> 4.6656 | N13: =M13*(1+Hypothesis!$F$3) -> 5.038848 | O13: =N13*(1+Hypothesis!$F$3) -> 5.4419558 | P13: =O13*(1+Hypothesis!$F$3) -> 5.8773123
B14: marketing cost | C14: -2 | D14: =(C14*(1+Hypothesis!$C$4)) -> -2.3 | E14: =(D14*(1+Hypothesis!$C$4)) -> -2.645 | F14: =(E14*(1+Hypothesis!$C$4)) -> -3.04175 | G14: =(F14*(1+Hypothesis!$C$4)) -> -3.4980125 | H14: =(G14*(1+Hypothesis!$C$4)) -> -4.0227144 | J14: other operating payables | K14: -1.8 | L14: =K14*(1+Hypothesis!$F$3) -> -1.944 | M14: =L14*(1+Hypothesis!$F$3) -> -2.09952 | N14: =M14*(1+Hypothesis!$F$3) -> -2.2674816 | O14: =N14*(1+Hypothesis!$F$3) -> -2.4488801 | P14: =O14*(1+Hypothesis!$F$3) -> -2.6447905
B15: logistic cost | C15: -3 | D15: =(C15*(1+Hypothesis!$C$4)) -> -3.45 | E15: =(D15*(1+Hypothesis!$C$4)) -> -3.9675 | F15: =(E15*(1+Hypothesis!$C$4)) -> -4.562625 | G15: =(F15*(1+Hypothesis!$C$4)) -> -5.2470187 | H15: =(G15*(1+Hypothesis!$C$4)) -> -6.0340716 | J15: NTWC | K15: =SUM(K12:K14) -> 7.2 | L15: =SUM(L12:L14) -> 7.776 | M15: =SUM(M12:M14) -> 8.39808 | N15: =SUM(N12:N14) -> 9.0699264 | O15: =SUM(O12:O14) -> 9.7955205 | P15: =SUM(P12:P14) -> 10.579162
B16: advisory cost | C16: -1 | D16: =(C16*(1+Hypothesis!$C$4)) -> -1.15 | E16: =(D16*(1+Hypothesis!$C$4)) -> -1.3225 | F16: =(E16*(1+Hypothesis!$C$4)) -> -1.520875 | G16: =(F16*(1+Hypothesis!$C$4)) -> -1.7490062 | H16: =(G16*(1+Hypothesis!$C$4)) -> -2.0113572 | J16: NWC | K16: =K11+K15 -> 16.2 | L16: =L11+L15 -> 17.496 | M16: =M11+M15 -> 18.89568 | N16: =N11+N15 -> 20.407334 | O16: =O11+O15 -> 22.039921 | P16: =P11+P15 -> 23.803115
B17: general and adm cost | C17: -4 | D17: =(C17*(1+Hypothesis!$C$4)) -> -4.6 | E17: =(D17*(1+Hypothesis!$C$4)) -> -5.29 | F17: =(E17*(1+Hypothesis!$C$4)) -> -6.0835 | G17: =(F17*(1+Hypothesis!$C$4)) -> -6.996025 | H17: =(G17*(1+Hypothesis!$C$4)) -> -8.0454287 | J17: PROVISIONS | K17: -3 | L17: =K17*(1+Hypothesis!$F$3) -> -3.24 | M17: =L17*(1+Hypothesis!$F$3) -> -3.4992 | N17: =M17*(1+Hypothesis!$F$3) -> -3.779136 | O17: =N17*(1+Hypothesis!$F$3) -> -4.0814669 | P17: =O17*(1+Hypothesis!$F$3) -> -4.4079842
B18: leasing cost | C18: -2 | D18: =(C18*(1+Hypothesis!$C$4)) -> -2.3 | E18: =(D18*(1+Hypothesis!$C$4)) -> -2.645 | F18: =(E18*(1+Hypothesis!$C$4)) -> -3.04175 | G18: =(F18*(1+Hypothesis!$C$4)) -> -3.4980125 | H18: =(G18*(1+Hypothesis!$C$4)) -> -4.0227144 | J18: NET OPERATING INVESTED CAPITAL | K18: =K8+K16+K17 -> 63.2 | L18: =L8+L16+L17 -> 68.256 | M18: =M8+M16+M17 -> 73.71648 | N18: =N8+N16+N17 -> 79.613798 | O18: =O8+O16+O17 -> 85.982902 | P18: =P8+P16+P17 -> 92.861534
B19: EBITDA | C19: =C10+C11 -> 31 | D19: =D10+D11 -> 40.65 | E19: =E10+E11 -> 52.7475 | F19: =F10+F11 -> 67.859625 | G19: =G10+G11 -> 86.678569 | H19: =H10+H11 -> 110.04835 | J19: SURPLUS ASSET | K19: 7 | L19: =K19*(1+Hypothesis!$F$3) -> 7.56 | M19: =L19*(1+Hypothesis!$F$3) -> 8.1648 | N19: =M19*(1+Hypothesis!$F$3) -> 8.817984 | O19: =N19*(1+Hypothesis!$F$3) -> 9.5234227 | P19: =O19*(1+Hypothesis!$F$3) -> 10.285297
B20: op cost (no cash) | C20: =SUM(C21:C24) -> -8.5 | D20: =SUM(D21:D24) -> -9.775 | E20: =SUM(E21:E24) -> -11.24125 | F20: =SUM(F21:F24) -> -12.927437 | G20: =SUM(G21:G24) -> -14.866553 | H20: =SUM(H21:H24) -> -17.096536 | J20: Invested Capital | K20: =K18+K19 -> 70.2 | L20: =L18+L19 -> 75.816 | M20: =M18+M19 -> 81.88128 | N20: =N18+N19 -> 88.431782 | O20: =O18+O19 -> 95.506325 | P20: =P18+P19 -> 103.14683
B21: ammortization | C21: -2 | D21: =(C21*(1+Hypothesis!$C$4)) -> -2.3 | E21: =(D21*(1+Hypothesis!$C$4)) -> -2.645 | F21: =(E21*(1+Hypothesis!$C$4)) -> -3.04175 | G21: =(F21*(1+Hypothesis!$C$4)) -> -3.4980125 | H21: =(G21*(1+Hypothesis!$C$4)) -> -4.0227144 | J21: equity | K21: 55 | L21: =K21*(1+Hypothesis!$F$3) -> 59.4 | M21: =L21*(1+Hypothesis!$F$3) -> 64.152 | N21: =M21*(1+Hypothesis!$F$3) -> 69.28416 | O21: =N21*(1+Hypothesis!$F$3) -> 74.826893 | P21: =O21*(1+Hypothesis!$F$3) -> 80.813044
B22: depreciation | C22: -4 | D22: =(C22*(1+Hypothesis!$C$4)) -> -4.6 | E22: =(D22*(1+Hypothesis!$C$4)) -> -5.29 | F22: =(E22*(1+Hypothesis!$C$4)) -> -6.0835 | G22: =(F22*(1+Hypothesis!$C$4)) -> -6.996025 | H22: =(G22*(1+Hypothesis!$C$4)) -> -8.0454287 | J22: debt | K22: 15.2 | L22: =K22*(1+Hypothesis!$F$3) -> 16.416 | M22: =L22*(1+Hypothesis!$F$3) -> 17.72928 | N22: =M22*(1+Hypothesis!$F$3) -> 19.147622 | O22: =N22*(1+Hypothesis!$F$3) -> 20.679432 | P22: =O22*(1+Hypothesis!$F$3) -> 22.333787
B23: impairment | C23: -1.5 | D23: =(C23*(1+Hypothesis!$C$4)) -> -1.725 | E23: =(D23*(1+Hypothesis!$C$4)) -> -1.98375 | F23: =(E23*(1+Hypothesis!$C$4)) -> -2.2813125 | G23: =(F23*(1+Hypothesis!$C$4)) -> -2.6235094 | H23: =(G23*(1+Hypothesis!$C$4)) -> -3.0170358 | J23: Capital structure | K23: =K21+K22 -> 70.2 | L23: =L21+L22 -> 75.816 | M23: =M21+M22 -> 81.88128 | N23: =N21+N22 -> 88.431782 | O23: =O21+O22 -> 95.506325 | P23: =P21+P22 -> 103.14683
B24: accrual to provisions | C24: -1 | D24: =(C24*(1+Hypothesis!$C$4)) -> -1.15 | E24: =(D24*(1+Hypothesis!$C$4)) -> -1.3225 | F24: =(E24*(1+Hypothesis!$C$4)) -> -1.520875 | G24: =(F24*(1+Hypothesis!$C$4)) -> -1.7490062 | H24: =(G24*(1+Hypothesis!$C$4)) -> -2.0113572
B25: EBIT | C25: =C19+C20 -> 22.5 | D25: =D19+D20 -> 30.875 | E25: =E19+E20 -> 41.50625 | F25: =F19+F20 -> 54.932187 | G25: =G19+G20 -> 71.812016 | H25: =H19+H20 -> 92.951818
B26: Net financial cost | C26: =SUM(C27:C29) -> -1.8 | D26: =SUM(D27:D29) -> -2.01 | E26: =SUM(E27:E29) -> -2.2395 | F26: =SUM(F27:F29) -> -2.489025 | G26: =SUM(G27:G29) -> -2.7586987 | H26: =SUM(H27:H29) -> -3.0480876
B27: interest on debt | C27: -2 | D27: =(C27*(1+Hypothesis!$C$4)) -> -2.3 | E27: =(D27*(1+Hypothesis!$C$4)) -> -2.645 | F27: =(E27*(1+Hypothesis!$C$4)) -> -3.04175 | G27: =(F27*(1+Hypothesis!$C$4)) -> -3.4980125 | H27: =(G27*(1+Hypothesis!$C$4)) -> -4.0227144
B28: other financial cost | C28: -1 | D28: =(C28*(1+Hypothesis!$C$4)) -> -1.15 | E28: =(D28*(1+Hypothesis!$C$4)) -> -1.3225 | F28: =(E28*(1+Hypothesis!$C$4)) -> -1.520875 | G28: =(F28*(1+Hypothesis!$C$4)) -> -1.7490062 | H28: =(G28*(1+Hypothesis!$C$4)) -> -2.0113572
B29: financial revenues | C29: 1.2 | D29: =(C29*(1+Hypothesis!$C$3)) -> 1.44 | E29: =(D29*(1+Hypothesis!$C$3)) -> 1.728 | F29: =(E29*(1+Hypothesis!$C$3)) -> 2.0736 | G29: =(F29*(1+Hypothesis!$C$3)) -> 2.48832 | H29: =(G29*(1+Hypothesis!$C$3)) -> 2.985984
B30: EBT op | C30: =C25+C26 -> 20.7 | D30: =D25+D26 -> 28.865 | E30: =E25+E26 -> 39.26675 | F30: =F25+F26 -> 52.443162 | G30: =G25+G26 -> 69.053317 | H30: =H25+H26 -> 89.90373
B31: Non-op cost | C31: -3 | D31: =(C31*(1+Hypothesis!$C$4)) -> -3.45 | E31: =(D31*(1+Hypothesis!$C$4)) -> -3.9675 | F31: =(E31*(1+Hypothesis!$C$4)) -> -4.562625 | G31: =(F31*(1+Hypothesis!$C$4)) -> -5.2470187 | H31: =(G31*(1+Hypothesis!$C$4)) -> -6.0340716
B32: EBT | C32: =C30+C31 -> 17.7 | D32: =D30+D31 -> 25.415 | E32: =E30+E31 -> 35.29925 | F32: =F30+F31 -> 47.880538 | G32: =G30+G31 -> 63.806298 | H32: =H30+H31 -> 83.869659
B33: TAXES | C33: =-C32*Hypothesis!$C$5 -> -3.894 | D33: =-D32*Hypothesis!$C$5 -> -5.5913 | E33: =-E32*Hypothesis!$C$5 -> -7.765835 | F33: =-F32*Hypothesis!$C$5 -> -10.533718 | G33: =-G32*Hypothesis!$C$5 -> -14.037386 | H33: =-H32*Hypothesis!$C$5 -> -18.451325
B34: NET INCOME | C34: =C32+C33 -> 13.806 | D34: =D32+D33 -> 19.8237 | E34: =E32+E33 -> 27.533415 | F34: =F32+F33 -> 37.346819 | G34: =G32+G33 -> 49.768913 | H34: =H32+H33 -> 65.418334

Sheet FLUSSI
B1: =Enterprise_Data!K3+1 -> 2021 | C1: =B1+1 -> 2022 | D1: =C1+1 -> 2023 | E1: =D1+1 -> 2024 | F1: =E1+1 -> 2025
A2: FCFF | B2: =Enterprise_Data!D25*(1-Hypothesis!$C$5)-Enterprise_Data!C20-(Enterprise_Data!L8-Enterprise_Data!K8)-(Enterprise_Data!L16-Enterprise_Data!K16) -> 27.2865 | C2: =Enterprise_Data!E25*(1-Hypothesis!$C$5)-Enterprise_Data!D20-(Enterprise_Data!M8-Enterprise_Data!L8)-(Enterprise_Data!M16-Enterprise_Data!L16) -> 36.430195 | D2: =Enterprise_Data!F25*(1-Hypothesis!$C$5)-Enterprise_Data!E20-(Enterprise_Data!N8-Enterprise_Data!M8)-(Enterprise_Data!N16-Enterprise_Data!M16) -> 47.911102 | E2: =Enterprise_Data!G25*(1-Hypothesis!$C$5)-Enterprise_Data!F20-(Enterprise_Data!O8-Enterprise_Data!N8)-(Enterprise_Data!O16-Enterprise_Data!N16) -> 62.269375 | F2: =Enterprise_Data!H25*(1-Hypothesis!$C$5)-Enterprise_Data!G20-(Enterprise_Data!P8-Enterprise_Data!O8)-(Enterprise_Data!P16-Enterprise_Data!O16) -> 80.163822
A3: FCFE | B3: =Enterprise_Data!C34-Enterprise_Data!C20-(Enterprise_Data!L8-Enterprise_Data!K8)-(Enterprise_Data!L16-Enterprise_Data!K16) -> 17.01 | C3: =Enterprise_Data!D34-Enterprise_Data!D20-(Enterprise_Data!M8-Enterprise_Data!L8)-(Enterprise_Data!M16-Enterprise_Data!L16) -> 23.87902 | D3: =Enterprise_Data!E34-Enterprise_Data!E20-(Enterprise_Data!N8-Enterprise_Data!M8)-(Enterprise_Data!N16-Enterprise_Data!M16) -> 32.597411 | E3: =Enterprise_Data!F34-Enterprise_Data!F20-(Enterprise_Data!O8-Enterprise_Data!N8)-(Enterprise_Data!O16-Enterprise_Data!N16) -> 43.602822 | F3: =Enterprise_Data!G34-Enterprise_Data!G20-(Enterprise_Data!P8-Enterprise_Data!O8)-(Enterprise_Data!P16-Enterprise_Data!O16) -> 57.430316

Sheet Hypothesis
B3: R Growth | C3: 0.2 | E3: STRUCTURE GROWTH | F3: 0.08
B4: Cost Growth | C4: 0.15
B5: TAXES | C5: 0.22
